comodo_api/__init__.py
comodo_api/comodo_api.py
comodo_api-0.3.0.dist-info/DESCRIPTION.rst
comodo_api-0.3.0.dist-info/LICENSE.txt
comodo_api-0.3.0.dist-info/METADATA
comodo_api-0.3.0.dist-info/RECORD
comodo_api-0.3.0.dist-info/WHEEL
comodo_api-0.3.0.dist-info/metadata.json
comodo_api-0.3.0.dist-info/top_level.txt
